keras_mdn_layer/__init__.py
keras_mdn_layer/tests/__init__.py
keras_mdn_layer/tests/test_mdn.py
keras_mdn_layer-0.4.4.dist-info/LICENSE.md
keras_mdn_layer-0.4.4.dist-info/METADATA
keras_mdn_layer-0.4.4.dist-info/WHEEL
keras_mdn_layer-0.4.4.dist-info/RECORD
