Metadata-Version: 2.1
Name: keras-mdn-layer
Version: 0.4.4
Summary: An MDN Layer for Keras using TensorFlow's distributions module
Home-page: https://github.com/cpmpercussion/keras-mdn-layer
License: MIT
Keywords: mixture density layer,neural network,machine learning
Author: Charles Martin
Author-email: cpm@charlesmartin.au
Requires-Python: ==3.11.*
Classifier: License :: OSI Approved :: MIT License
Classifier: Programming Language :: Python :: 3
Classifier: Programming Language :: Python :: 3.11
Classifier: Topic :: Scientific/Engineering :: Artificial Intelligence
Requires-Dist: numpy (>=1.26.4,<2.0.0)
Requires-Dist: tensorflow (==2.15.0) ; sys_platform == "darwin" and platform_machine == "x86_64"
Requires-Dist: tensorflow (==2.15.0) ; sys_platform == "linux" and platform_machine == "x86_64"
Requires-Dist: tensorflow (>=2.15.0,<2.16.0) ; sys_platform == "win32"
Requires-Dist: tensorflow-macos (==2.15.0) ; sys_platform == "darwin" and platform_machine == "arm64"
Requires-Dist: tensorflow-probability (==0.23.0)
Project-URL: Repository, https://github.com/cpmpercussion/keras-mdn-layer
